PureNote/__init__.py
PureNote/custom_exception.py
PureNote/logger.py
PureNote/render.py
purenote-0.0.5.dist-info/LICENSE
purenote-0.0.5.dist-info/METADATA
purenote-0.0.5.dist-info/WHEEL
purenote-0.0.5.dist-info/top_level.txt
purenote-0.0.5.dist-info/RECORD
